QianguQianduanTuwenJiaochengFix1/README.md
QianguQianduanTuwenJiaochengFix1/__init__.py
QianguQianduanTuwenJiaochengFix1/__main__.py
QianguQianduanTuwenJiaochengFix1/file.epub
QianguQianduanTuwenJiaochengFix1/index.html
QianguQianduanTuwenJiaochengFix1/css/__init__.py
QianguQianduanTuwenJiaochengFix1/css/annotations.css
QianguQianduanTuwenJiaochengFix1/css/main.css
QianguQianduanTuwenJiaochengFix1/css/normalize.css
QianguQianduanTuwenJiaochengFix1/css/popup.css
QianguQianduanTuwenJiaochengFix1/font/__init__.py
QianguQianduanTuwenJiaochengFix1/font/fontello.eot
QianguQianduanTuwenJiaochengFix1/font/fontello.svg
QianguQianduanTuwenJiaochengFix1/font/fontello.ttf
QianguQianduanTuwenJiaochengFix1/font/fontello.woff
QianguQianduanTuwenJiaochengFix1/img/__init__.py
QianguQianduanTuwenJiaochengFix1/img/annotator-glyph-sprite.png
QianguQianduanTuwenJiaochengFix1/img/annotator-icon-sprite.png
QianguQianduanTuwenJiaochengFix1/img/apple-touch-icon.png
QianguQianduanTuwenJiaochengFix1/img/cancelfullscreen.png
QianguQianduanTuwenJiaochengFix1/img/close.png
QianguQianduanTuwenJiaochengFix1/img/fullscreen.png
QianguQianduanTuwenJiaochengFix1/img/loader.gif
QianguQianduanTuwenJiaochengFix1/img/menu-icon.png
QianguQianduanTuwenJiaochengFix1/img/save.png
QianguQianduanTuwenJiaochengFix1/img/saved.png
QianguQianduanTuwenJiaochengFix1/img/settings-s.png
QianguQianduanTuwenJiaochengFix1/img/settings.png
QianguQianduanTuwenJiaochengFix1/img/star.png
QianguQianduanTuwenJiaochengFix1/js/__init__.py
QianguQianduanTuwenJiaochengFix1/js/epub.js
QianguQianduanTuwenJiaochengFix1/js/epub.min.js
QianguQianduanTuwenJiaochengFix1/js/epub.min.map
QianguQianduanTuwenJiaochengFix1/js/hooks.min.js
QianguQianduanTuwenJiaochengFix1/js/hooks.min.map
QianguQianduanTuwenJiaochengFix1/js/reader.js
QianguQianduanTuwenJiaochengFix1/js/reader.js.map
QianguQianduanTuwenJiaochengFix1/js/reader.min.js
QianguQianduanTuwenJiaochengFix1/js/reader.min.map
QianguQianduanTuwenJiaochengFix1/js/hooks/__init__.py
qiangu_qianduan_tuwen_jiaocheng_fix1-2025.3.25.1.dist-info/METADATA
qiangu_qianduan_tuwen_jiaocheng_fix1-2025.3.25.1.dist-info/WHEEL
qiangu_qianduan_tuwen_jiaocheng_fix1-2025.3.25.1.dist-info/entry_points.txt
qiangu_qianduan_tuwen_jiaocheng_fix1-2025.3.25.1.dist-info/top_level.txt
qiangu_qianduan_tuwen_jiaocheng_fix1-2025.3.25.1.dist-info/RECORD
